plbm/AptManage.py
plbm/Cmd.py
plbm/Docker.py
plbm/Dpkg.py
plbm/FileManagement.py
plbm/Iptables.py
plbm/Jurisdiction.py
plbm/NetManagement.py
plbm/NetStatus.py
plbm/OsInfo.py
plbm/Package.py
plbm/Service.py
plbm/Source.py
plbm/Yum.py
plbm/__init__.py
plbm/get.py
plbm/logger.py
plbm-1.3.4.dist-info/LICENSE
plbm-1.3.4.dist-info/METADATA
plbm-1.3.4.dist-info/WHEEL
plbm-1.3.4.dist-info/top_level.txt
plbm-1.3.4.dist-info/RECORD
