Metadata-Version: 2.1
Name: plbm
Version: 1.3.4
Summary: 这是一个Linux管理脚本的基础库，通过对Linux基本功能进行封装，实现快速开发的效果
Home-page: https://gitee.com/liumou_site/PythonLinuxBasicModule
Author: 坐公交也用券
Author-email: liumou.site@qq.com
License: UNKNOWN
Platform: UNKNOWN
Classifier: Programming Language :: Python :: 3
Classifier: License :: OSI Approved :: MIT License
Classifier: Operating System :: OS Independent
Requires-Python: >=3.0
